example/__init__.py
example/actions.py
example/addons.py
example/admin.py
example/apps.py
example/graph_models.py
example/models.py
example/query.py
example/serializer.py
example/tests.py
example/urls.py
example/views.py
example/migrations/__init__.py
gWeaver/__init__.py
gWeaver/actions.py
gWeaver/admin.py
gWeaver/apps.py
gWeaver/models.py
gWeaver/tests.py
gWeaver/views.py
gWeaver/base/__init__.py
gWeaver/base/base_models.py
gWeaver/base/graph_actions.py
gWeaver/base/graph_query.py
gWeaver/base/graph_views.py
gWeaver/base/node_connector.py
gWeaver/base/response_constructor.py
gWeaver/base/schema_generator.py
gWeaver/management/__init__.py
gWeaver/management/commands/__init__.py
gWeaver/management/commands/_private.py
gWeaver/management/commands/graph_migrate.py
gWeaver/managers/__init__.py
gWeaver/managers/client.py
gWeaver/migrations/__init__.py
graph/__init__.py
graph/asgi.py
graph/settings.py
graph/urls.py
graph/wsgi.py
gWeaver-1.0.6.dist-info/LICENSE.txt
gWeaver-1.0.6.dist-info/METADATA
gWeaver-1.0.6.dist-info/WHEEL
gWeaver-1.0.6.dist-info/top_level.txt
gWeaver-1.0.6.dist-info/RECORD
